beluga/__init__.py
beluga/__main__.py
beluga/beluga.py
beluga/release.py
beluga/continuation/__init__.py
beluga/continuation/continuation.py
beluga/continuation/guess_generators.py
beluga/numeric/__init__.py
beluga/numeric/bvp_solvers/BaseAlgorithm.py
beluga/numeric/bvp_solvers/SPBVP.py
beluga/numeric/bvp_solvers/Shooting.py
beluga/numeric/bvp_solvers/__init__.py
beluga/numeric/compilation/LocalCompiler.py
beluga/numeric/compilation/__init__.py
beluga/numeric/compilation/component_compilation.py
beluga/numeric/compilation/jit.py
beluga/numeric/data_classes/NumericProblem.py
beluga/numeric/data_classes/Trajectory.py
beluga/numeric/data_classes/__init__.py
beluga/numeric/data_classes/trajectory_mappers.py
beluga/numeric/ivp_solvers/__init__.py
beluga/numeric/ivp_solvers/ivpsol.py
beluga/numeric/numerical_derivatives/__init__.py
beluga/numeric/numerical_derivatives/complex_step.py
beluga/numeric/numerical_derivatives/finite_diff.py
beluga/symbolic/__init__.py
beluga/symbolic/data_classes/__init__.py
beluga/symbolic/data_classes/components_structures.py
beluga/symbolic/data_classes/mapping_functions.py
beluga/symbolic/data_classes/symbolic_problem.py
beluga/symbolic/differential_geometry/__init__.py
beluga/symbolic/differential_geometry/differential_geometry.py
beluga/symbolic/special_functions/__init__.py
beluga/symbolic/special_functions/custom_functions.py
beluga/symbolic/special_functions/tables.py
beluga/utils/__init__.py
beluga/utils/helper_functions.py
beluga/utils/logging.py
beluga/utils/storage.py
beluga-0.4.0.1.dist-info/AUTHORS
beluga-0.4.0.1.dist-info/LICENSE
beluga-0.4.0.1.dist-info/METADATA
beluga-0.4.0.1.dist-info/WHEEL
beluga-0.4.0.1.dist-info/entry_points.txt
beluga-0.4.0.1.dist-info/top_level.txt
beluga-0.4.0.1.dist-info/RECORD
