Metadata-Version: 2.1
Name: beluga
Version: 0.4.0.1
Summary: A general purpose indirect trajectory optimization framework.
Home-page: https://github.com/Rapid-Design-of-Systems-Laboratory/beluga
Author: Sean Nolan
Author-email: nolans@pudue.edu
License: MIT
Platform: any
Classifier: Intended Audience :: Developers
Classifier: Intended Audience :: Science/Research
Classifier: License :: OSI Approved :: MIT License
Classifier: Operating System :: OS Independent
Classifier: Programming Language :: Python
Classifier: Programming Language :: Python :: 3
Classifier: Programming Language :: Python :: 3.7
Classifier: Programming Language :: Python :: 3.8
Classifier: Programming Language :: Python :: 3.9
Classifier: Topic :: Scientific/Engineering
Classifier: Topic :: Scientific/Engineering :: Mathematics
Classifier: Topic :: Scientific/Engineering :: Physics
Requires-Python: >3.7
Requires-Dist: cloudpickle
Requires-Dist: docopt (>=0.6.2)
Requires-Dist: liepack (>=0.1.1)
Requires-Dist: llvmlite (>=0.28.0)
Requires-Dist: matplotlib (>=2.2.2)
Requires-Dist: numba (>=0.47.0)
Requires-Dist: numexpr (>=2.6.8)
Requires-Dist: numpy (>=1.16.3)
Requires-Dist: scipy (>=1.2.0)
Requires-Dist: sympy (>=1.5)
Requires-Dist: pathos (>=0.2.2.1)
Requires-Dist: PyYAML (>=5.0)
Requires-Dist: tqdm (>=4.31.0)
Provides-Extra: dev
Requires-Dist: coverage ; extra == 'dev'
Requires-Dist: coverage-badge ; extra == 'dev'
Requires-Dist: pylint ; extra == 'dev'
Requires-Dist: pytest (>=3.5.1) ; extra == 'dev'
Requires-Dist: pytest-cov (>=2.5.1) ; extra == 'dev'
Requires-Dist: pytest-describe (>=0.11.1) ; extra == 'dev'
Requires-Dist: sphinx ; extra == 'dev'
